cleanup/__init__.py
cleanup/clean.py
cleanup_pypi_sushantsur23-0.0.3.dist-info/LICENSE
cleanup_pypi_sushantsur23-0.0.3.dist-info/METADATA
cleanup_pypi_sushantsur23-0.0.3.dist-info/WHEEL
cleanup_pypi_sushantsur23-0.0.3.dist-info/top_level.txt
cleanup_pypi_sushantsur23-0.0.3.dist-info/RECORD
