Metadata-Version: 2.1
Name: cleanup-pypi-sushantsur23
Version: 0.0.3
Summary: implementation of cleanup data
Home-page: https://github.com/sushantsur23/cleanup_pypi.git
Author: sushantsur23
Author-email: sushant_sur23@yahoo.co.in
License: UNKNOWN
Project-URL: Bug Tracker, https://github.com/sushantsur23/cleanup_pypi/issues
Platform: UNKNOWN
Classifier: Programming Language :: Python :: 3
Classifier: License :: OSI Approved :: MIT License
Classifier: Operating System :: OS Independent
Requires-Python: >=3.7
License-File: LICENSE
Requires-Dist: numpy
Requires-Dist: pandas
Requires-Dist: sklearn
Requires-Dist: statsmodels
